vima/__init__.py
vima/cc.py
vima/vis.py
vima/data/__init__.py
vima/data/patchcollection.py
vima/data/samples.py
vima/ingest/__init__.py
vima/ingest/ingest.py
vima/models/__init__.py
vima/models/resnet_vae.py
vima/models/resnetlight_decoder.py
vima/models/resnetlight_encoder.py
vima/models/simple_vae.py
vima/models/vae.py
vima/train/__init__.py
vima/train/logging.py
vima/train/training.py
vima_spatial-0.1.4.dist-info/METADATA
vima_spatial-0.1.4.dist-info/WHEEL
vima_spatial-0.1.4.dist-info/top_level.txt
vima_spatial-0.1.4.dist-info/RECORD
