Metadata-Version: 2.4
Name: vima-spatial
Version: 0.1.4
Summary: variationa inference-based microniche analysis
Home-page: https://github.com/yakirr/vima
Author: Yakir Reshef
Author-email: yreshef@broadinstitute.org
Project-URL: Bug Tracker, https://github.com/yakirr/vima/issues
Project-URL: Tutorial, https://github.com/yakirr/vima/blob/main/README.md
Classifier: Programming Language :: Python :: 3
Classifier: License :: OSI Approved :: MIT License
Classifier: Operating System :: OS Independent
Requires-Python: >=3.12.3
Requires-Dist: torch>=2.3.0
Requires-Dist: torchvision>=0.18.0
Requires-Dist: anndata>=0.10.7
Requires-Dist: matplotlib
Requires-Dist: multianndata
Requires-Dist: numpy>=1.26.4
Requires-Dist: scanpy
Requires-Dist: cv2
Requires-Dist: xarray
Requires-Dist: seaborn
Requires-Dist: pandas>=2.2.3
Requires-Dist: scipy
Requires-Dist: mpl_toolkits
Requires-Dist: cna>=0.2.2
Requires-Dist: tqdm
Requires-Dist: skimage
Requires-Dist: IPython
